setup.py
aiomongo/__init__.py
aiomongo/auth.py
aiomongo/bulk.py
aiomongo/client.py
aiomongo/collection.py
aiomongo/command_cursor.py
aiomongo/connection.py
aiomongo/cursor.py
aiomongo/database.py
aiomongo/grid_file.py
aiomongo/gridfs.py
aiomongo/utils.py
aiomongo.egg-info/PKG-INFO
aiomongo.egg-info/SOURCES.txt
aiomongo.egg-info/dependency_links.txt
aiomongo.egg-info/requires.txt
aiomongo.egg-info/top_level.txt