Metadata-Version: 1.1
Name: aiomongo
Version: 0.1
Summary: Asynchronous Python driver for MongoDB <http://www.mongodb.org>
Home-page: https://github.com/ZeoAlliance/aiomongo
Author: Dmytro Domashevskyi
Author-email: domash@zeoalliance.com
License: Apache License, Version 2.0
Keywords: mongo,mongodb,pymongo,aiomongo
Platform: UNKNOWN
Classifier: Intended Audience :: Developers
Classifier: License :: OSI Approved :: Apache Software License
Classifier: Operating System :: MacOS :: MacOS X
Classifier: Operating System :: Microsoft :: Windows
Classifier: Operating System :: POSIX
Classifier: Programming Language :: Python
Classifier: Programming Language :: Python :: 3.5
Classifier: Programming Language :: Python :: 3.6
Classifier: Programming Language :: Python :: Implementation :: CPython
Classifier: Topic :: Database
